{
    "usuarios": [
      {
        "nome": "Shepardy",
        "chaveAcesso": "1846018bbc715385",
        "nivelAcesso": "desenvolvedor",
        "saldo": 5000
      },
      {
        "nome": "Usuário 2",
        "chaveAcesso": "chave456",
        "nivelAcesso": "patrocinador",
        "saldo": 20
      },
      {
        "nome": "Usuário 3",
        "chaveAcesso": "chave789",
        "nivelAcesso": "personalizado",
        "saldo": 100
      }
    ],

    "itens": [
      {
        "nivel": "T1",
        "user": "Shepardy",
        "valor": 100,
        "descricao": "Descrição do item 1",
        "link": "https://github.com/repositorio/pull-request3",
        "status": "pendente"
      },
      {
        "nivel": "T2",
        "user": "user2",
        "valor": 200,
        "descricao": "Descrição do item 2",
        "link": "https://github.com/repositorio/pull-request5",
        "status": "pendente"
      },
      {
        "nivel": "T1",
        "user": "Shepardy",
        "valor": 50,
        "descricao": "Descrição do item 10",
        "link": "https://github.com/repositorio/pull-request10",
        "status": "pendente"
      }

    ]
}
  